.DS_Store
dmm/__init__.py
dmm/dmm.py
dmm_search3-2.3.dist-info/LICENSE.txt
dmm_search3-2.3.dist-info/METADATA
dmm_search3-2.3.dist-info/WHEEL
dmm_search3-2.3.dist-info/top_level.txt
dmm_search3-2.3.dist-info/RECORD
