Metadata-Version: 2.1
Name: dmm-search3
Version: 2.3
Summary: DMM Web API Version 3.0 Wrapper for Python3
Home-page: https://github.com/miya/dmm-search3
Author: miya
Author-email: m0zurillex@gmail.com
License: MIT
Keywords: python3,dmm,REST API
Platform: UNKNOWN
Classifier: Programming Language :: Python :: 3.7
Requires-Dist: lxml
Requires-Dist: requests
Requires-Dist: youtube-dl
Requires-Dist: beautifulsoup4
